{
  "brand": {
    "기타": {
      "total_cost": 18750637.0,
      "total_revenue": 36057960.0,
      "total_conversions": 903.0,
      "roas": 192.3,
      "cpa": 20764.83,
      "cvr": 3.33
    }
  },
  "channel": {
    "메타_전환": {
      "total_cost": 18700970.0,
      "total_revenue": 36057960.0,
      "total_conversions": 903.0,
      "roas": 192.81,
      "cpa": 20709.82,
      "cvr": 3.33
    },
    "메타_트래픽": {
      "total_cost": 1027563.0,
      "total_revenue": 241400.0,
      "total_conversions": 9.0,
      "roas": 23.49,
      "cpa": 114173.67,
      "cvr": 0.22
    },
    "메타_도달": {
      "total_cost": 235857.0,
      "total_revenue": 0.0,
      "total_conversions": 0.0,
      "roas": 0.0,
      "cpa": 0,
      "cvr": 0.0
    }
  },
  "product": {
    "기타": {
      "total_cost": 18750637.0,
      "total_revenue": 36057960.0,
      "total_conversions": 903.0,
      "roas": 192.3,
      "cpa": 20764.83,
      "cvr": 3.33
    }
  },
  "promotion": {
    "기타": {
      "total_cost": 18750637.0,
      "total_revenue": 36057960.0,
      "total_conversions": 903.0,
      "roas": 192.3,
      "cpa": 20764.83,
      "cvr": 3.33
    }
  }
}